grpc_interceptor/__init__.py
grpc_interceptor/client.py
grpc_interceptor/exception_to_status.py
grpc_interceptor/exceptions.py
grpc_interceptor/py.typed
grpc_interceptor/server.py
grpc_interceptor/testing/__init__.py
grpc_interceptor/testing/dummy_client.py
grpc_interceptor/testing/protos/__init__.py
grpc_interceptor/testing/protos/dummy.proto
grpc_interceptor/testing/protos/dummy_pb2.py
grpc_interceptor/testing/protos/dummy_pb2.pyi
grpc_interceptor/testing/protos/dummy_pb2_grpc.py
grpc_interceptor-0.15.0.dist-info/LICENSE
grpc_interceptor-0.15.0.dist-info/WHEEL
grpc_interceptor-0.15.0.dist-info/METADATA
grpc_interceptor-0.15.0.dist-info/RECORD
