Metadata-Version: 2.1
Name: grpc-interceptor
Version: 0.15.0
Summary: Simplifies gRPC interceptors
Home-page: https://github.com/d5h-foss/grpc-interceptor
License: MIT
Keywords: grpc,interceptor
Author: Dan Hipschman
Requires-Python: >=3.6.1,<4.0.0
Classifier: License :: OSI Approved :: MIT License
Classifier: Programming Language :: Python :: 3
Classifier: Programming Language :: Python :: 3.7
Classifier: Programming Language :: Python :: 3.8
Provides-Extra: testing
Requires-Dist: grpcio (>=1.32.0,<2.0.0)
Requires-Dist: protobuf (>=3.6.0); extra == "testing"
Project-URL: Documentation, https://grpc-interceptor.readthedocs.io
Project-URL: Repository, https://github.com/d5h-foss/grpc-interceptor
